shangshan/__init__.py
shangshan/download.py
shangshan/utils.py
shangshan-0.1.1.dist-info/LICENSE
shangshan-0.1.1.dist-info/METADATA
shangshan-0.1.1.dist-info/WHEEL
shangshan-0.1.1.dist-info/top_level.txt
shangshan-0.1.1.dist-info/RECORD
